aiotele/__init__.py
aiotele/api.py
aiotele/client.py
aiotele/constants.py
aiotele/logger.py
aiotele/types.py
aiotele/update_manager.py
aiotele/utils.py
aiotele-1.0.1.dist-info/LICENSE
aiotele-1.0.1.dist-info/METADATA
aiotele-1.0.1.dist-info/WHEEL
aiotele-1.0.1.dist-info/top_level.txt
aiotele-1.0.1.dist-info/RECORD
